gofer_service/__init__.py
gofer_service/create_database.py
gofer_service/dump_grades.py
gofer_service/gofer_nb.py
gofer_service/grade_assignment.py
gofer_service/lti_keys.py
gofer_service/secrets/gh_key.yaml
gofer_service/secrets/gke_key.yaml
gofer_service-0.1.11.dist-info/LICENSE
gofer_service-0.1.11.dist-info/METADATA
gofer_service-0.1.11.dist-info/WHEEL
gofer_service-0.1.11.dist-info/entry_points.txt
gofer_service-0.1.11.dist-info/top_level.txt
gofer_service-0.1.11.dist-info/RECORD
