Metadata-Version: 2.1
Name: gofer-service
Version: 0.1.11
Summary: Grading Service for Edx 8x courses
Home-page: https://github.com/data-8/gofer_service
Author: Vincent Su and Sean Morris
Author-email: sean.smorris@berkeley.edu
License: UNKNOWN
Platform: UNKNOWN
Classifier: Programming Language :: Python :: 3
Classifier: License :: OSI Approved :: MIT License
Classifier: Operating System :: OS Independent
Requires-Python: >=3.8
License-File: LICENSE
